tinkoff_acquiring/__init__.py
tinkoff_acquiring/client.py
tinkoff_acquiring-0.1.5.dist-info/LICENSE
tinkoff_acquiring-0.1.5.dist-info/METADATA
tinkoff_acquiring-0.1.5.dist-info/WHEEL
tinkoff_acquiring-0.1.5.dist-info/top_level.txt
tinkoff_acquiring-0.1.5.dist-info/RECORD
