Metadata-Version: 2.1
Name: tinkoff-acquiring
Version: 0.1.5
Summary: A Python client for Tinkoff Acquiring API
Home-page: https://github.com/sm1ky/tinkoff_acquiring
Author: Artem
Author-email: support@sm1ky.com
Classifier: Programming Language :: Python :: 3
Classifier: License :: OSI Approved :: MIT License
Classifier: Operating System :: OS Independent
Requires-Python: >=3.10
License-File: LICENSE
Requires-Dist: httpx
